pmprophet/__init__.py
pmprophet/model.py
pmprophet-0.2.8.dist-info/METADATA
pmprophet-0.2.8.dist-info/WHEEL
pmprophet-0.2.8.dist-info/top_level.txt
pmprophet-0.2.8.dist-info/RECORD
