Metadata-Version: 2.1
Name: pmprophet
Version: 0.2.8
Summary: Pymc3-based universal time series prediction and decomposition library inspired by Facebook Prophet
Home-page: https://github.com/luke14free/pm-prophet
Author: Luca Giacomel
Author-email: luca.giacomel@gmail.com
License: Apache License 2.0
Platform: UNKNOWN
Requires-Dist: matplotlib
Requires-Dist: numpy
Requires-Dist: pandas (>=0.23.0)
Requires-Dist: pymc3
